fastapi_rest_framework/__init__.py
fastapi_rest_framework-0.0.2.dist-info/LICENSE
fastapi_rest_framework-0.0.2.dist-info/WHEEL
fastapi_rest_framework-0.0.2.dist-info/METADATA
fastapi_rest_framework-0.0.2.dist-info/RECORD
